{
  "employees": [
    {
      "name": "Caio Lucas Pereira da Silva",
      "gender": "male",
      "status": true,
      "cpf": "123.456.789-10",
      "phoneNumber": "(33) 99887-7665",
      "salary": "R$ 100000,00",
      "department": "marketing",
      "id": 1
    },
    {
      "name": "Lucas Kaio",
      "gender": "male",
      "status": true,
      "cpf": "109.876.543-21",
      "phoneNumber": "(99) 33445-5667",
      "salary": "R$ 10,00",
      "department": "Desenvolvimento",
      "id": 2
    },
    {
      "name": "Luis Enersto",
      "gender": "male",
      "status": true,
      "cpf": "765.890.321-45",
      "phoneNumber": "(11) 92233-0066",
      "salary": "R$ 3000,00",
      "department": "Suporte",
      "id": 3
    },
    {
      "name": "Antonella Miranda",
      "gender": "female",
      "status": true,
      "cpf": "589.380.512-39",
      "phoneNumber": "(33) 97755-4431",
      "salary": "R$ 10000,00",
      "department": "Desenvolvimento",
      "id": 4
    }
  ]
}